{
  "plan": "Plan",
  "farm": "Farm",
  "default_autosuggest_placeholder": "Select item",
  "add_character_placeholder": "Add character",
  "select_weapon_placeholder": "Select weapon",
  "select_artifacts_placeholder": "Select artifacts",
  "empty_autosuggest_label": "Not found",
  "character": "Character",
  "ascension": "Ascension",
  "talent": "Talent",
  "weapon": "Weapon",
  "artifact": "Artifact",
  "monster_drop": "Monster Drop",
  "boss_drop": "Boss Drop",
  "weekly_boss": "Weekly Boss",
  "local_specialty": "Local Specialty",
  "weapon_ascension": "Weapon Ascension",
  "talent_ascension": "Talent Ascension",
  "expand_all": "Expand All",
  "collapse_all": "Collapse All",
  "reset": "Reset",
  "no_item_found": "No Item Found",
  "anemo": "Anemo",
  "cryo": "Cyro",
  "pyro": "Pyro",
  "hydro": "Hydro",
  "electro": "Electro",
  "geo": "Geo",
  "dendro": "Dendro",
  "sword": "Sword",
  "bow": "Bow",
  "claymore": "Claymore",
  "catalyst": "Catalyst",
  "polearm": "Polearm",
  "mondstant": "Mondstant",
  "liyue": "Liyue",
  "inazuma": "Inazuma",
  "dvalin": "Stormterror Dvalin",
  "andrius": "Lupus Boreas, Dominator of Wolves",
  "childe": "Tartaglia",
  "azhdaha": "Azhdaha",
  "la_signora": "Signora",
  "mikoto": "Magatsu Mitake Narukami no Mikoto",
  "traveler_anemo": "Traveler (Anemo)",
  "traveler_geo": "Traveler (Geo)",
  "traveler_electro": "Traveler (Electro)",
  "bit_of_aerosiderite": "Bit of Aerosiderite",
  "boreal_wolfs_broken_fang": "Boreal Wolf's Broken Fang",
  "boreal_wolfs_cracked_tooth": "Boreal Wolf's Cracked Tooth",
  "boreal_wolfs_milk_tooth": "Boreal Wolf's Milk Tooth",
  "boreal_wolfs_nostalgia": "Boreal Wolf's Nostalgia",
  "chains_of_the_dandelion_gladiator": "Chains of the Dandelion Gladiator",
  "chunk_of_aerosiderite": "Chunk of Aerosiderite",
  "coral_branch_of_a_distant_sea": "Coral Branch of a Distant Sea",
  "debris_of_decarabians_city": "Debris of Decarabian's City",
  "divine_body_from_guyun": "Divine Body from Guyun",
  "dream_of_the_dandelion_gladiator": "Dream of the Dandelion Gladiator",
  "fetters_of_the_dandelion_gladiator": "Fetters of the Dandelion Gladiator",
  "fragment_of_decarabians_epic": "Fragment of Decarabian's Epic",
  "golden_branch_of_a_distant_sea": "Golden Branch of a Distant Sea",
  "grain_of_aerosiderite": "Grain of Aerosiderite",
  "jade_branch_of_a_distant_sea": "Jade Branch of a Distant Sea",
  "jeweled_branch_of_a_distant_sea": "Jeweled Branch of a Distant Sea",
  "luminous_sands_from_guyun": "Luminous Sands from Guyun",
  "lustrous_stone_from_guyun": "Lustrous Stone from Guyun",
  "mask_of_the_kijin": "Mask of the Kijin",
  "mask_of_the_onehorned": "Mask of the One-Horned",
  "mask_of_the_tigers_bite": "Mask of the Tiger's Bite",
  "mask_of_the_wicked_lieutenant": "Mask of the Wicked Lieutenant",
  "mist_veiled_gold_elixir": "Mist Veiled Gold Elixir",
  "mist_veiled_lead_elixir": "Mist Veiled Lead Elixir",
  "mist_veiled_mercury_elixir": "Mist Veiled Mercury Elixir",
  "mist_veiled_primo_elixir": "Mist Veiled Primo Elixir",
  "narukamis_affection": "Narukami's Affection",
  "narukamis_joy": "Narukami's Joy",
  "narukamis_valor": "Narukami's Valor",
  "narukamis_wisdom": "Narukami's Wisdom",
  "piece_of_aerosiderite": "Piece of Aerosiderite",
  "relic_from_guyun": "Relic from Guyun",
  "scattered_piece_of_decarabians_dream": "Scattered Piece of Decarabian's Dream",
  "shackles_of_the_dandelion_gladiator": "Shackles of the Dandelion Gladiator",
  "tile_of_decarabians_tower": "Tile of Decarabian's Tower",
  "agents_sacrificial_knife": "Agent's Sacrificial Knife",
  "agnidus_agate_chunk": "Agnidus Agate Chunk",
  "agnidus_agate_fragment": "Agnidus Agate Fragment",
  "agnidus_agate_gemstone": "Agnidus Agate Gemstone",
  "agnidus_agate_sliver": "Agnidus Agate Sliver",
  "ashen_heart": "Ashen Heart",
  "basalt_pillar": "Basalt Pillar",
  "black_bronze_horn": "Black Bronze Horn",
  "black_crystal_horn": "Black Crystal Horn",
  "bloodjade_branch": "Bloodjade Branch",
  "brilliant_diamond_chunk": "Brilliant Diamond Chunk",
  "brilliant_diamond_fragment": "Brilliant Diamond Fragment",
  "brilliant_diamond_gemstone": "Brilliant Diamond Gemstone",
  "brilliant_diamond_sliver": "Brilliant Diamond Sliver",
  "chaos_axis": "Chaos Axis",
  "chaos_circuit": "Chaos Circuit",
  "chaos_core": "Chaos Core",
  "chaos_device": "Chaos Device",
  "chaos_gear": "Chaos Gear",
  "chaos_oculus": "Chaos Oculus",
  "cleansing_heart": "Cleansing Heart",
  "concealed_claw": "Concealed Claw",
  "concealed_talon": "Concealed Talon",
  "concealed_unguis": "Concealed Unguis",
  "crystalline_bloom": "Crystalline Bloom",
  "crystalline_cyst_dust": "Crystalline Cyst Dust",
  "crystal_prism": "Crystal Prism",
  "damaged_mask": "Damaged Mask",
  "dark_statuette": "Dark Statuette",
  "dead_ley_line_branch": "Dead Ley Line Branch",
  "dead_ley_line_leaves": "Dead Ley Line Leaves",
  "deathly_statuette": "Deathly Statuette",
  "dew_of_repudiation": "Dew of Repudiation",
  "dismal_prism": "Dismal Prism",
  "divining_scroll": "Divining Scroll",
  "dragonheirs_false_fin": "Dragonheir's False Fin",
  "dragon_lords_crown": "Dragon Lord's Crown",
  "dvalins_claw": "Dvalin's Claw",
  "dvalins_plume": "Dvalin's Plume",
  "dvalins_sigh": "Dvalin's Sigh",
  "energy_nectar": "Energy Nectar",
  "everflame_seed": "Everflame Seed",
  "famed_handguard": "Famed Handguard",
  "firm_arrowhead": "Firm Arrowhead",
  "forbidden_curse_scroll": "Forbidden Curse Scroll",
  "fossilized_bone_shard": "Fossilized Bone Shard",
  "fragile_bone_shard": "Fragile Bone Shard",
  "fungal_spores": "Fungal Spores",
  "gilded_scale": "Gilded Scale",
  "gloomy_statuette": "Gloomy Statuette",
  "golden_raven_insignia": "Golden Raven Insignia",
  "heavy_horn": "Heavy Horn",
  "hellfire_butterfly": "Hellfire Butterfly",
  "hoarfrost_core": "Hoarfrost Core",
  "hunters_sacrificial_knife": "Hunter's Sacrificial Knife",
  "hurricane_seed": "Hurricane Seed",
  "inspectors_sacrificial_knife": "Inspector's Sacrificial Knife",
  "juvenile_jade": "Juvenile Jade",
  "kageuchi_handguard": "Kageuchi Handguard",
  "ley_line_sprout": "Ley Line Sprout",
  "lieutenants_insignia": "Lieutenant's Insignia",
  "lightning_prism": "Lightning Prism",
  "luminescent_pollen": "Luminescent Pollen",
  "marionette_core": "Marionette Core",
  "mist_grass": "Mist Grass",
  "mist_grass_pollen": "Mist Grass Pollen",
  "mist_grass_wick": "Mist Grass Wick",
  "molten_moment": "Molten Moment",
  "mudra_of_the_malefic_general": "Mudra of the Malefic General",
  "nagadus_emerald_chunk": "Nagadus Emerald Chunk",
  "nagadus_emerald_fragment": "Nagadus Emerald Fragment",
  "nagadus_emerald_gemstone": "Nagadus Emerald Gemstone",
  "nagadus_emerald_sliver": "Nagadus Emerald Sliver",
  "old_handguard": "Old Handguard",
  "ominous_mask": "Ominous Mask",
  "perpetual_heart": "Perpetual Heart",
  "polarizing_prism": "Polarizing Prism",
  "prithiva_topaz_chunk": "Prithiva Topaz Chunk",
  "prithiva_topaz_fragment": "Prithiva Topaz Fragment",
  "prithiva_topaz_gemstone": "Prithiva Topaz Gemstone",
  "prithiva_topaz_sliver": "Prithiva Topaz Sliver",
  "recruits_insignia": "Recruit's Insignia",
  "riftborn_regalia": "Riftborn Regalia",
  "ring_of_boreas": "Ring of Boreas",
  "runic_fang": "Runic Fang",
  "sealed_scroll": "Sealed Scroll",
  "sergeants_insignia": "Sergeant's Insignia",
  "shadow_of_the_warrior": "Shadow of the Warrior",
  "shard_of_a_foul_legacy": "Shard of a Foul Legacy",
  "sharp_arrowhead": "Sharp Arrowhead",
  "shimmering_nectar": "Shimmering Nectar",
  "shivada_jade_chunk": "Shivada Jade Chunk",
  "shivada_jade_fragment": "Shivada Jade Fragment",
  "shivada_jade_gemstone": "Shivada Jade Gemstone",
  "shivada_jade_sliver": "Shivada Jade Sliver",
  "silver_raven_insignia": "Silver Raven Insignia",
  "slime_concentrate": "Slime Concentrate",
  "slime_condensate": "Slime Condensate",
  "slime_secretions": "Slime Secretions",
  "smoldering_pearl": "Smoldering Pearl",
  "spectral_heart": "Spectral Heart",
  "spectral_husk": "Spectral Husk",
  "spectral_nucleus": "Spectral Nucleus",
  "spirit_locket_of_boreas": "Spirit Locket of Boreas",
  "stained_mask": "Stained Mask",
  "storm_beads": "Storm Beads",
  "sturdy_bone_shard": "Sturdy Bone Shard",
  "tail_of_boreas": "Tail of Boreas",
  "tears_of_the_calamitous_god": "Tears of the Calamitous God",
  "the_meaning_of_aeons": "The Meaning of Aeons",
  "treasure_hoarder_insignia": "Treasure Hoarder Insignia",
  "tusk_of_monoceros_caeli": "Tusk of Monoceros Caeli",
  "vajrada_amethyst_chunk": "Vajrada Amethyst Chunk",
  "vajrada_amethyst_fragment": "Vajrada Amethyst Fragment",
  "vajrada_amethyst_gemstone": "Vajrada Amethyst Gemstone",
  "vajrada_amethyst_sliver": "Vajrada Amethyst Sliver",
  "varunada_lazurite_chunk": "Varunada Lazurite Chunk",
  "varunada_lazurite_fragment": "Varunada Lazurite Fragment",
  "varunada_lazurite_gemstone": "Varunada Lazurite Gemstone",
  "varunada_lazurite_sliver": "Varunada Lazurite Sliver",
  "vayuda_turquoise_chunk": "Vayuda Turquoise Chunk",
  "vayuda_turquoise_fragment": "Vayuda Turquoise Fragment",
  "vayuda_turquoise_gemstone": "Vayuda Turquoise Gemstone",
  "vayuda_turquoise_sliver": "Vayuda Turquoise Sliver",
  "weathered_arrowhead": "Weathered Arrowhead",
  "whopperflower_nectar": "Whopperflower Nectar",
  "crown_of_insight": "Crown of Insight",
  "guide_to_ballad": "Guide to Ballad",
  "guide_to_diligence": "Guide to Diligence",
  "guide_to_elegance": "Guide to Elegance",
  "guide_to_freedom": "Guide to Freedom",
  "guide_to_gold": "Guide to Gold",
  "guide_to_light": "Guide to Light",
  "guide_to_prosperity": "Guide to Prosperity",
  "guide_to_resistance": "Guide to Resistance",
  "guide_to_transience": "Guide to Transience",
  "philosophies_of_ballad": "Philosophies of Ballad",
  "philosophies_of_diligence": "Philosophies of Diligence",
  "philosophies_of_elegance": "Philosophies of Elegance",
  "philosophies_of_freedom": "Philosophies of Freedom",
  "philosophies_of_gold": "Philosophies of Gold",
  "philosophies_of_light": "Philosophies of Light",
  "philosophies_of_prosperity": "Philosophies of Prosperity",
  "philosophies_of_resistance": "Philosophies of Resistance",
  "philosophies_of_transience": "Philosophies of Transience",
  "teachings_of_ballad": "Teachings of Ballad",
  "teachings_of_diligence": "Teachings of Diligence",
  "teachings_of_elegance": "Teachings of Elegance",
  "teachings_of_freedom": "Teachings of Freedom",
  "teachings_of_gold": "Teachings of Gold",
  "teachings_of_light": "Teachings of Light",
  "teachings_of_prosperity": "Teachings of Prosperity",
  "teachings_of_resistance": "Teachings of Resistance",
  "teachings_of_transience": "Teachings of Transience",
  "calla_lily": "Calla Lily",
  "cecilia": "Cecilia",
  "dandelion_seed": "Dandelion Seed",
  "philanemo_mushroom": "Philanemo Mushroom",
  "small_lamp_grass": "Small Lamp Grass",
  "valberry": "Valberry",
  "windwheel_aster": "Windwheel Aster",
  "wolfhook": "Wolfhook",
  "cor_lapis": "Cor Lapis",
  "glaze_lily": "Glaze Lily",
  "jueyun_chili": "Jueyun Chili",
  "noctilucous_jade": "Noctilucous Jade",
  "qingxin": "Qingxin",
  "silk_flower": "Silk Flower",
  "starconch": "Starconch",
  "violetgrass": "Violetgrass",
  "amakumo_fruit": "Amakumo Fruit",
  "crystal_marrow": "Crystal Marrow",
  "dendrobium": "Dendrobium",
  "fluorescent_fungus": "Fluorescent Fungus",
  "naku_weed": "Naku Weed",
  "onikabuto": "Onikabuto",
  "sakura_bloom": "Sakura Bloom",
  "sango_pearl": "Sango Pearl",
  "sea_ganoderma": "Sea Ganoderma",
  "adventurer": "Adventurer",
  "archaic_petra": "Archaic Petra",
  "berserker": "Berserker",
  "blizzard_strayer": "Blizzard Strayer",
  "bloodstained_chivalry": "Bloodstained Chivalry",
  "brave_heart": "Brave Heart",
  "crimson_witch_of_flames": "Crimson Witch of Flames",
  "defenders_will": "Defender's Will",
  "echoes_of_an_offering": "Echoes of an Offering",
  "emblem_of_severed_fate": "Emblem of Severed Fate",
  "gambler": "Gambler",
  "gladiators_finale": "Gladiator's Finale",
  "heart_of_depth": "Heart of Depth",
  "husk_of_opulent_dreams": "Husk of Opulent Dreams",
  "instructor": "Instructor",
  "lavawalker": "Lavawalker",
  "lucky_dog": "Lucky Dog",
  "maiden_beloved": "Maiden Beloved",
  "martial_artist": "Martial Artist",
  "noblesse_oblige": "Noblesse Oblige",
  "oceanhued_clam": "Ocean-Hued Clam",
  "pale_flame": "Pale Flame",
  "prayers_for_destiny": "Prayers for Destiny",
  "prayers_for_illumination": "Prayers for Illumination",
  "prayers_for_wisdom": "Prayers for Wisdom",
  "prayers_to_springtime": "Prayers to Springtime",
  "resolution_of_sojourner": "Resolution of Sojourner",
  "retracing_bolide": "Retracing Bolide",
  "scholar": "Scholar",
  "shimenawas_reminiscence": "Shimenawa's Reminiscence",
  "tenacity_of_the_millelith": "Tenacity of the Millelith",
  "the_exile": "The Exile",
  "thundering_fury": "Thundering Fury",
  "thundersoother": "Thundersoother",
  "tiny_miracle": "Tiny Miracle",
  "traveling_doctor": "Traveling Doctor",
  "vermillion_hereafter": "Vermillion Hereafter",
  "viridescent_venerer": "Viridescent Venerer",
  "wanderers_troupe": "Wanderer's Troupe",
  "aether": "Aether",
  "albedo": "Albedo",
  "aloy": "Aloy",
  "amber": "Amber",
  "arataki_itto": "Arataki Itto",
  "barbara": "Barbara",
  "beidou": "Beidou",
  "bennett": "Bennett",
  "chongyun": "Chongyun",
  "diluc": "Diluc",
  "diona": "Diona",
  "eula": "Eula",
  "fischl": "Fischl",
  "ganyu": "Ganyu",
  "gorou": "Gorou",
  "hu_tao": "Hu Tao",
  "jean": "Jean",
  "kaedehara_kazuha": "Kaedehara Kazuha",
  "kaeya": "Kaeya",
  "kamisato_ayaka": "Kamisato Ayaka",
  "kamisato_ayato": "Kamisato Ayato",
  "keqing": "Keqing",
  "klee": "Klee",
  "kujou_sara": "Kujou Sara",
  "lisa": "Lisa",
  "lumine": "Lumine",
  "mona": "Mona",
  "ningguang": "Ningguang",
  "noelle": "Noelle",
  "qiqi": "Qiqi",
  "raiden_shogun": "Raiden Shogun",
  "razor": "Razor",
  "rosaria": "Rosaria",
  "sangonomiya_kokomi": "Sangonomiya Kokomi",
  "sayu": "Sayu",
  "shenhe": "Shenhe",
  "sucrose": "Sucrose",
  "tartaglia": "Tartaglia",
  "thoma": "Thoma",
  "venti": "Venti",
  "xiangling": "Xiangling",
  "xiao": "Xiao",
  "xingqiu": "Xingqiu",
  "xinyan": "Xinyan",
  "yae_miko": "Yae Miko",
  "yanfei": "Yanfei",
  "yoimiya": "Yoimiya",
  "yun_jin": "Yun Jin",
  "zhongli": "Zhongli",
  "akuoumaru": "Akuoumaru",
  "alley_hunter": "Alley Hunter",
  "amenoma_kageuchi": "Amenoma Kageuchi",
  "amos_bow": "Amos' Bow",
  "apprentices_notes": "Apprentice's Notes",
  "aquila_favonia": "Aquila Favonia",
  "beginners_protector": "Beginner's Protector",
  "blackcliff_agate": "Blackcliff Agate",
  "blackcliff_longsword": "Blackcliff Longsword",
  "blackcliff_pole": "Blackcliff Pole",
  "blackcliff_slasher": "Blackcliff Slasher",
  "blackcliff_warbow": "Blackcliff Warbow",
  "black_tassel": "Black Tassel",
  "bloodtainted_greatsword": "Bloodtainted Greatsword",
  "calamity_queller": "Calamity Queller",
  "cinnabar_spindle": "Cinnabar Spindle",
  "compound_bow": "Compound Bow",
  "cool_steel": "Cool Steel",
  "crescent_pike": "Crescent Pike",
  "dark_iron_sword": "Dark Iron Sword",
  "deathmatch": "Deathmatch",
  "debate_club": "Debate Club",
  "dodoco_tales": "Dodoco Tales",
  "dragons_bane": "Dragon's Bane",
  "dragonspine_spear": "Dragonspine Spear",
  "dull_blade": "Dull Blade",
  "elegy_for_the_end": "Elegy for the End",
  "emerald_orb": "Emerald Orb",
  "engulfing_lightning": "Engulfing Lightning",
  "everlasting_moonglow": "Everlasting Moonglow",
  "eye_of_perception": "Eye of Perception",
  "favonius_codex": "Favonius Codex",
  "favonius_greatsword": "Favonius Greatsword",
  "favonius_lance": "Favonius Lance",
  "favonius_sword": "Favonius Sword",
  "favonius_warbow": "Favonius Warbow",
  "ferrous_shadow": "Ferrous Shadow",
  "festering_desire": "Festering Desire",
  "fillet_blade": "Fillet Blade",
  "freedomsworn": "Freedom-Sworn",
  "frostbearer": "Frostbearer",
  "hakushin_ring": "Hakushin Ring",
  "halberd": "Halberd",
  "hamayumi": "Hamayumi",
  "haran_geppaku_futsu": "Haran Geppaku Futsu",
  "harbinger_of_dawn": "Harbinger of Dawn",
  "hunters_bow": "Hunter's Bow",
  "iron_point": "Iron Point",
  "iron_sting": "Iron Sting",
  "kaguras_verity": "Kagura's Verity",
  "katsuragikiri_nagamasa": "Katsuragikiri Nagamasa",
  "kitain_cross_spear": "Kitain Cross Spear",
  "lions_roar": "Lion's Roar",
  "lithic_blade": "Lithic Blade",
  "lithic_spear": "Lithic Spear",
  "lost_prayer_to_the_sacred_winds": "Lost Prayer to the Sacred Winds",
  "luxurious_sealord": "Luxurious Sea-Lord",
  "magic_guide": "Magic Guide",
  "mappa_mare": "Mappa Mare",
  "memory_of_dust": "Memory of Dust",
  "messenger": "Messenger",
  "mistsplitter_reforged": "Mistsplitter Reforged",
  "mitternachts_waltz": "Mitternachts Waltz",
  "mouuns_moon": "Mouun's Moon",
  "oathsworn_eye": "Oathsworn Eye",
  "old_mercs_pal": "Old Merc's Pal",
  "otherworldly_story": "Otherworldly Story",
  "pocket_grimoire": "Pocket Grimoire",
  "polar_star": "Polar Star",
  "predator": "Predator",
  "primordial_jade_cutter": "Primordial Jade Cutter",
  "primordial_jade_wingedspear": "Primordial Jade Winged-Spear",
  "prototype_amber": "Prototype Amber",
  "prototype_archaic": "Prototype Archaic",
  "prototype_crescent": "Prototype Crescent",
  "prototype_rancour": "Prototype Rancour",
  "prototype_starglitter": "Prototype Starglitter",
  "rainslasher": "Rainslasher",
  "raven_bow": "Raven Bow",
  "recurve_bow": "Recurve Bow",
  "redhorn_stonethresher": "Redhorn Stonethresher",
  "royal_bow": "Royal Bow",
  "royal_greatsword": "Royal Greatsword",
  "royal_grimoire": "Royal Grimoire",
  "royal_longsword": "Royal Longsword",
  "royal_spear": "Royal Spear",
  "rust": "Rust",
  "sacrificial_bow": "Sacrificial Bow",
  "sacrificial_fragments": "Sacrificial Fragments",
  "sacrificial_greatsword": "Sacrificial Greatsword",
  "sacrificial_sword": "Sacrificial Sword",
  "seasoned_hunters_bow": "Seasoned Hunter's Bow",
  "serpent_spine": "Serpent Spine",
  "sharpshooters_oath": "Sharpshooter's Oath",
  "silver_sword": "Silver Sword",
  "skyrider_greatsword": "Skyrider Greatsword",
  "skyrider_sword": "Skyrider Sword",
  "skyward_atlas": "Skyward Atlas",
  "skyward_blade": "Skyward Blade",
  "skyward_harp": "Skyward Harp",
  "skyward_pride": "Skyward Pride",
  "skyward_spine": "Skyward Spine",
  "slingshot": "Slingshot",
  "snowtombed_starsilver": "Snow-Tombed Starsilver",
  "solar_pearl": "Solar Pearl",
  "song_of_broken_pines": "Song of Broken Pines",
  "staff_of_homa": "Staff of Homa",
  "summit_shaper": "Summit Shaper",
  "sword_of_descension": "Sword of Descension",
  "the_alley_flash": "The Alley Flash",
  "the_bell": "The Bell",
  "the_black_sword": "The Black Sword",
  "the_catch": "The Catch",
  "the_flute": "The Flute",
  "the_stringless": "The Stringless",
  "the_unforged": "The Unforged",
  "the_viridescent_hunt": "The Viridescent Hunt",
  "the_widsith": "The Widsith",
  "thrilling_tales_of_dragon_slayers": "Thrilling Tales of Dragon Slayers",
  "thundering_pulse": "Thundering Pulse",
  "travelers_handy_sword": "Traveler's Handy Sword",
  "twin_nephrite": "Twin Nephrite",
  "vortex_vanquisher": "Vortex Vanquisher",
  "waster_greatsword": "Waster Greatsword",
  "wavebreakers_fin": "Wavebreaker's Fin",
  "whiteblind": "Whiteblind",
  "white_iron_greatsword": "White Iron Greatsword",
  "white_tassel": "White Tassel",
  "windblume_ode": "Windblume Ode",
  "wine_and_song": "Wine and Song",
  "wolfs_gravestone": "Wolf's Gravestone",
  "domain_of_blessing_autumn_hunt": "Domain of Blessing: Autumn Hunt",
  "domain_of_blessing_dance_of_steel": "Domain of Blessing: Dance of Steel",
  "domain_of_blessing_elegaic_rime": "Domain of Blessing: Elegaic Rime",
  "domain_of_blessing_fires_of_purification": "Domain of Blessing: Fires of Purification",
  "domain_of_blessing_frost": "Domain of Blessing: Frost",
  "domain_of_blessing_necropolis": "Domain of Blessing: Necropolis",
  "domain_of_blessing_spring": "Domain of Blessing: Spring",
  "domain_of_blessing_stone_chamber": "Domain of Blessing: Stone Chamber",
  "domain_of_blessing_unyielding": "Domain of Blessing: Unyielding",
  "domain_of_forgery_altar_of_sands": "Domain of Forgery: Altar of Sands",
  "domain_of_forgery_city_of_reflections": "Domain of Forgery: City of Reflections",
  "domain_of_forgery_ruins_of_thirsting_capital": "Domain of Forgery: Ruins of Thirsting Capital",
  "domain_of_forgery_sand_burial": "Domain of Forgery: Sand Burial",
  "domain_of_forgery_submerged_valley": "Domain of Forgery: Submerged Valley",
  "domain_of_forgery_sunken_sands": "Domain of Forgery: Sunken Sands",
  "domain_of_forgery_thundercloud_altar": "Domain of Forgery: Thundercloud Altar",
  "domain_of_forgery_thundering_ruins": "Domain of Forgery: Thundering Ruins",
  "domain_of_forgery_trial_grounds_of_thunder": "Domain of Forgery: Trial Grounds of Thunder",
  "domain_of_mastery_altar_of_flames": "Domain of Mastery: Altar of Flames",
  "domain_of_mastery_circle_of_embers": "Domain of Mastery: Circle of Embers",
  "domain_of_mastery_frosted_altar": "Domain of Mastery: Frosted Altar",
  "domain_of_mastery_frozen_abyss": "Domain of Mastery: Frozen Abyss",
  "domain_of_mastery_heart_of_the_flames": "Domain of Mastery: Heart of the Flames",
  "domain_of_mastery_realm_of_slumber": "Domain of Mastery: Realm of Slumber",
  "domain_of_mastery_reign_of_violet": "Domain of Mastery: Reign of Violet",
  "domain_of_mastery_thundering_valley": "Domain of Mastery: Thundering Valley",
  "domain_of_mastery_vineinfested_ruins": "Domain of Mastery: Vine-Infested Ruins"
}
