[
  {
    "id": "domain_of_blessing_autumn_hunt",
    "region": "Inazuma",
    "type": "Artifacts",
    "reward": [
      "resolution_of_sojourner",
      "tiny_miracle",
      "shimenawas_reminiscence",
      "emblem_of_severed_fate"
    ]
  },
  {
    "id": "domain_of_blessing_dance_of_steel",
    "region": "Mondstadt",
    "type": "Artifacts",
    "reward": [
      "traveling_doctor",
      "tiny_miracle",
      "viridescent_venerer",
      "maiden_beloved"
    ]
  },
  {
    "id": "domain_of_blessing_elegaic_rime",
    "region": "Mondstadt",
    "type": "Artifacts",
    "reward": [
      "defenders_will",
      "gambler",
      "blizzard_strayer",
      "heart_of_depth"
    ]
  },
  {
    "id": "domain_of_blessing_fires_of_purification",
    "region": "Mondstadt",
    "type": "Artifacts",
    "reward": [
      "adventurer",
      "resolution_of_sojourner",
      "thundering_fury",
      "thundersoother"
    ]
  },
  {
    "id": "domain_of_blessing_frost",
    "region": "Liyue",
    "type": "Artifacts",
    "reward": [
      "defenders_will",
      "martial_artist",
      "crimson_witch_of_flames",
      "lavawalker"
    ]
  },
  {
    "id": "domain_of_blessing_necropolis",
    "region": "Inazuma",
    "type": "Artifacts",
    "reward": [
      "defenders_will",
      "brave_heart",
      "husk_of_opulent_dreams",
      "oceanhued_clam"
    ]
  },
  {
    "id": "domain_of_blessing_spring",
    "region": "Liyue",
    "type": "Artifacts",
    "reward": [
      "lucky_dog",
      "brave_heart",
      "archaic_petra",
      "retracing_bolide"
    ]
  },
  {
    "id": "domain_of_blessing_stone_chamber",
    "region": "Liyue",
    "type": "Artifacts",
    "reward": [
      "gambler",
      "scholar",
      "bloodstained_chivalry",
      "noblesse_oblige"
    ]
  },
  {
    "id": "domain_of_blessing_unyielding",
    "region": "Mondstadt",
    "type": "Artifacts",
    "reward": [
      "brave_heart",
      "martial_artist",
      "tenacity_of_the_millelith",
      "pale_flame"
    ]
  },
  {
    "id": "domain_of_forgery_altar_of_sands",
    "region": "Inazuma",
    "type": "Weapon Ascension Materials",
    "daysofweek": [
      "Tuesday",
      "Friday",
      "Sunday"
    ],
    "reward": [
      "narukamis_wisdom",
      "narukamis_joy",
      "narukamis_affection",
      "narukamis_valor"
    ]
  },
  {
    "id": "domain_of_forgery_city_of_reflections",
    "region": "Mondstadt",
    "type": "Weapon Ascension Materials",
    "daysofweek": [
      "Monday",
      "Thursday",
      "Sunday"
    ],
    "reward": [
      "tile_of_decarabians_tower",
      "debris_of_decarabians_city",
      "fragment_of_decarabians_epic",
      "scattered_piece_of_decarabians_dream"
    ]
  },
  {
    "id": "domain_of_forgery_ruins_of_thirsting_capital",
    "region": "Mondstadt",
    "type": "Weapon Ascension Materials",
    "daysofweek": [
      "Wednesday",
      "Saturday",
      "Sunday"
    ],
    "reward": [
      "fetters_of_the_dandelion_gladiator",
      "chains_of_the_dandelion_gladiator",
      "shackles_of_the_dandelion_gladiator",
      "dream_of_the_dandelion_gladiator"
    ]
  },
  {
    "id": "domain_of_forgery_sand_burial",
    "region": "Inazuma",
    "type": "Weapon Ascension Materials",
    "daysofweek": [
      "Wednesday",
      "Saturday",
      "Sunday"
    ],
    "reward": [
      "mask_of_the_wicked_lieutenant",
      "mask_of_the_tigers_bite",
      "mask_of_the_onehorned",
      "mask_of_the_kijin"
    ]
  },
  {
    "id": "domain_of_forgery_submerged_valley",
    "region": "Mondstadt",
    "type": "Weapon Ascension Materials",
    "daysofweek": [
      "Tuesday",
      "Friday",
      "Sunday"
    ],
    "reward": [
      "boreal_wolfs_milk_tooth",
      "boreal_wolfs_cracked_tooth",
      "boreal_wolfs_broken_fang",
      "boreal_wolfs_nostalgia"
    ]
  },
  {
    "id": "domain_of_forgery_sunken_sands",
    "region": "Inazuma",
    "type": "Weapon Ascension Materials",
    "daysofweek": [
      "Monday",
      "Thursday",
      "Sunday"
    ],
    "reward": [
      "coral_branch_of_a_distant_sea",
      "jeweled_branch_of_a_distant_sea",
      "jade_branch_of_a_distant_sea",
      "golden_branch_of_a_distant_sea"
    ]
  },
  {
    "id": "domain_of_forgery_thundercloud_altar",
    "region": "Liyue",
    "type": "Weapon Ascension Materials",
    "daysofweek": [
      "Monday",
      "Thursday",
      "Sunday"
    ],
    "reward": [
      "luminous_sands_from_guyun",
      "lustrous_stone_from_guyun",
      "relic_from_guyun",
      "divine_body_from_guyun"
    ]
  },
  {
    "id": "domain_of_forgery_thundering_ruins",
    "region": "Liyue",
    "type": "Weapon Ascension Materials",
    "daysofweek": [
      "Tuesday",
      "Friday",
      "Sunday"
    ],
    "reward": [
      "mist_veiled_lead_elixir",
      "mist_veiled_mercury_elixir",
      "mist_veiled_gold_elixir",
      "mist_veiled_primo_elixir"
    ]
  },
  {
    "id": "domain_of_forgery_trial_grounds_of_thunder",
    "region": "Liyue",
    "type": "Weapon Ascension Materials",
    "daysofweek": [
      "Wednesday",
      "Saturday",
      "Sunday"
    ],
    "reward": [
      "grain_of_aerosiderite",
      "piece_of_aerosiderite",
      "bit_of_aerosiderite",
      "chunk_of_aerosiderite"
    ]
  },
  {
    "id": "domain_of_mastery_altar_of_flames",
    "region": "Mondstadt",
    "type": "Talent Level-Up Material",
    "daysofweek": [
      "Monday",
      "Thursday",
      "Sunday"
    ],
    "reward": [
      "teachings_of_prosperity",
      "guide_to_prosperity",
      "philosophies_of_prosperity"
    ]
  },
  {
    "id": "domain_of_mastery_circle_of_embers",
    "region": "Liyue",
    "type": "Talent Level-Up Material",
    "daysofweek": [
      "Wednesday",
      "Saturday",
      "Sunday"
    ],
    "reward": [
      "teachings_of_gold",
      "guide_to_gold",
      "philosophies_of_gold"
    ]
  },
  {
    "id": "domain_of_mastery_frosted_altar",
    "region": "Mondstadt",
    "type": "Talent Level-Up Material",
    "daysofweek": [
      "Monday",
      "Thursday",
      "Sunday"
    ],
    "reward": [
      "teachings_of_freedom",
      "guide_to_freedom",
      "philosophies_of_freedom"
    ]
  },
  {
    "id": "domain_of_mastery_frozen_abyss",
    "region": "Mondstadt",
    "type": "Talent Level-Up Material",
    "daysofweek": [
      "Tuesday",
      "Friday",
      "Sunday"
    ],
    "reward": [
      "teachings_of_resistance",
      "guide_to_resistance",
      "philosophies_of_resistance"
    ]
  },
  {
    "id": "domain_of_mastery_heart_of_the_flames",
    "region": "Liyue",
    "type": "Talent Level-Up Material",
    "daysofweek": [
      "Tuesday",
      "Friday",
      "Sunday"
    ],
    "reward": [
      "teachings_of_diligence",
      "guide_to_diligence",
      "philosophies_of_diligence"
    ]
  },
  {
    "id": "domain_of_mastery_realm_of_slumber",
    "region": "Mondstadt",
    "type": "Talent Level-Up Material",
    "daysofweek": [
      "Wednesday",
      "Saturday",
      "Sunday"
    ],
    "reward": [
      "teachings_of_ballad",
      "guide_to_ballad",
      "philosophies_of_ballad"
    ]
  },
  {
    "id": "domain_of_mastery_reign_of_violet",
    "region": "Inazuma",
    "type": "Talent Level-Up Material",
    "daysofweek": [
      "Monday",
      "Thursday",
      "Sunday"
    ],
    "reward": [
      "teachings_of_transience",
      "guide_to_transience",
      "philosophies_of_transience"
    ]
  },
  {
    "id": "domain_of_mastery_thundering_valley",
    "region": "Inazuma",
    "type": "Talent Level-Up Material",
    "daysofweek": [
      "Tuesday",
      "Friday",
      "Sunday"
    ],
    "reward": [
      "teachings_of_elegance",
      "guide_to_elegance",
      "philosophies_of_elegance"
    ]
  },
  {
    "id": "domain_of_mastery_vineinfested_ruins",
    "region": "Inazuma",
    "type": "Talent Level-Up Material",
    "daysofweek": [
      "Wednesday",
      "Saturday",
      "Sunday"
    ],
    "reward": [
      "teachings_of_light",
      "guide_to_light",
      "philosophies_of_light"
    ]
  }
]